tooluniverse/__init__.py
tooluniverse/_lazy_registry_static.py
tooluniverse/admetai_tool.py
tooluniverse/agentic_tool.py
tooluniverse/alphafold_tool.py
tooluniverse/arrayexpress_tool.py
tooluniverse/arxiv_tool.py
tooluniverse/base_rest_tool.py
tooluniverse/base_tool.py
tooluniverse/biogrid_tool.py
tooluniverse/biomodels_tool.py
tooluniverse/biorxiv_tool.py
tooluniverse/blast_tool.py
tooluniverse/boltz_tool.py
tooluniverse/build_optimizer.py
tooluniverse/cbioportal_tool.py
tooluniverse/cdc_tool.py
tooluniverse/cellosaurus_tool.py
tooluniverse/chem_tool.py
tooluniverse/civic_tool.py
tooluniverse/clinical_trials_tool.py
tooluniverse/clinvar_tool.py
tooluniverse/compose_tool.py
tooluniverse/core_tool.py
tooluniverse/crossref_tool.py
tooluniverse/ctg_tool.py
tooluniverse/custom_tool.py
tooluniverse/dailymed_tool.py
tooluniverse/dataset_tool.py
tooluniverse/dbfetch_tool.py
tooluniverse/dblp_tool.py
tooluniverse/dbpedia_tool.py
tooluniverse/dbsnp_tool.py
tooluniverse/default_config.py
tooluniverse/dgidb_tool.py
tooluniverse/doaj_tool.py
tooluniverse/doctor.py
tooluniverse/ebi_search_tool.py
tooluniverse/efo_tool.py
tooluniverse/emdb_tool.py
tooluniverse/ena_browser_tool.py
tooluniverse/encode_tool.py
tooluniverse/enrichr_tool.py
tooluniverse/ensembl_tool.py
tooluniverse/europe_pmc_tool.py
tooluniverse/exceptions.py
tooluniverse/execute_function.py
tooluniverse/extended_hooks.py
tooluniverse/fatcat_tool.py
tooluniverse/fda_pharmacogenomic_biomarkers_tool.py
tooluniverse/file_download_tool.py
tooluniverse/gbif_tool.py
tooluniverse/gdc_tool.py
tooluniverse/gene_ontology_tool.py
tooluniverse/generate_lazy_registry.py
tooluniverse/generate_tools.py
tooluniverse/genomics_gene_search_tool.py
tooluniverse/geo_tool.py
tooluniverse/ghost_tool.py
tooluniverse/gnomad_tool.py
tooluniverse/graphql_tool.py
tooluniverse/gtex_tool.py
tooluniverse/gtopdb_tool.py
tooluniverse/gwas_tool.py
tooluniverse/hal_tool.py
tooluniverse/hca_tool.py
tooluniverse/health_disparities_tool.py
tooluniverse-1.0.16.dist-info/licenses/LICENSE
tooluniverse-1.0.16.dist-info/METADATA
tooluniverse-1.0.16.dist-info/WHEEL
tooluniverse-1.0.16.dist-info/entry_points.txt
tooluniverse-1.0.16.dist-info/top_level.txt
tooluniverse-1.0.16.dist-info/RECORD
