Metadata-Version: 2.4
Name: tooluniverse
Version: 1.0.16
Summary: A comprehensive collection of scientific tools for Agentic AI, offering integration with the ToolUniverse SDK and MCP Server to support advanced scientific workflows.
Author-email: Shanghua Gao <shanghuagao@gmail.com>
Project-URL: Homepage, https://github.com/mims-harvard/ToolUniverse
Requires-Python: >=3.10
License-File: LICENSE
Requires-Dist: requests>=2.32.0
Requires-Dist: numpy>=2.2.0
Requires-Dist: sympy>=1.12.0
Requires-Dist: graphql-core>=3.2.0
Requires-Dist: fastapi>=0.116.0
Requires-Dist: uvicorn>=0.35.0
Requires-Dist: pydantic>=2.11.0
Requires-Dist: epam.indigo>=1.34.0
Requires-Dist: networkx>=3.4.0
Requires-Dist: openai>=1.107.0
Requires-Dist: pyyaml>=6.0.0
Requires-Dist: google-genai>=1.36.0
Requires-Dist: google-generativeai>=0.7.2
Requires-Dist: mcp[cli]>=1.9.3
Requires-Dist: fastmcp>=2.12.3
Requires-Dist: xmltodict>=1.0.0
Requires-Dist: lxml>=6.0.0
Requires-Dist: huggingface_hub>=0.34.0
Requires-Dist: jsonpath-ng>=1.6.0
Requires-Dist: rcsb-api>=1.4.0
Requires-Dist: fitz>=0.0.1.dev2
Requires-Dist: pandas>=2.2.3
Requires-Dist: setuptools<81.0.0,>=70.0.0
Requires-Dist: pdfplumber>=0.11.0
Requires-Dist: playwright>=1.55.0
Requires-Dist: faiss-cpu==1.12.0
Requires-Dist: flask>=2.0.0
Requires-Dist: aiohttp
Requires-Dist: beautifulsoup4>=4.12.0
Requires-Dist: python-dotenv>=1.0.0
Requires-Dist: markitdown[all]>=0.1.0
Requires-Dist: psutil>=5.9.0
Requires-Dist: ddgs>=9.0.0
Requires-Dist: pip>=25.3
Requires-Dist: jsonschema>=4.23.0
Provides-Extra: smolagents
Requires-Dist: smolagents>=1.22.0; extra == "smolagents"
Requires-Dist: gradio>=4.0.0; extra == "smolagents"
Provides-Extra: dev
Requires-Dist: pytest>=7.0; extra == "dev"
Requires-Dist: pytest-cov>=4.0; extra == "dev"
Requires-Dist: pytest-timeout>=2.3.1; extra == "dev"
Requires-Dist: pytest-mock>=3.14.0; extra == "dev"
Requires-Dist: pytest-asyncio>=0.21.0; extra == "dev"
Requires-Dist: pre-commit>=2.0; extra == "dev"
Requires-Dist: pytest-xdist>=3.0; extra == "dev"
Requires-Dist: pytest-html>=3.0; extra == "dev"
Requires-Dist: requests-mock>=1.12.1; extra == "dev"
Requires-Dist: ruff>=0.14.5; extra == "dev"
Provides-Extra: docs
Requires-Dist: sphinx>=4.0; extra == "docs"
Requires-Dist: furo>=2024.8.6; extra == "docs"
Requires-Dist: pydata-sphinx-theme>=0.15.0; extra == "docs"
Requires-Dist: sphinx-rtd-theme>=1.0; extra == "docs"
Requires-Dist: shibuya>=0.10.0; extra == "docs"
Requires-Dist: myst-parser>=0.18; extra == "docs"
Requires-Dist: linkify-it-py>=2.0.0; extra == "docs"
Requires-Dist: sphinx-autobuild>=2021.3.14; extra == "docs"
Requires-Dist: sphinx-copybutton>=0.5.0; extra == "docs"
Requires-Dist: sphinx-tabs>=3.2.0; extra == "docs"
Requires-Dist: sphinx-design>=0.3.0; extra == "docs"
Requires-Dist: sphinx-notfound-page>=0.8; extra == "docs"
Requires-Dist: sphinx-autodoc-typehints>=1.12.0; extra == "docs"
Provides-Extra: embedding
Requires-Dist: sentence-transformers>=5.1.0; extra == "embedding"
Requires-Dist: faiss-cpu==1.12.0; extra == "embedding"
Requires-Dist: huggingface_hub>=0.34.0; extra == "embedding"
Provides-Extra: ml
Requires-Dist: admet-ai>=1.2.0; extra == "ml"
Requires-Dist: sentence-transformers>=5.1.0; extra == "ml"
Requires-Dist: faiss-cpu==1.12.0; extra == "ml"
Requires-Dist: huggingface_hub>=0.34.0; extra == "ml"
Provides-Extra: graph
Requires-Dist: flask>=2.0.0; extra == "graph"
Requires-Dist: matplotlib>=3.5.0; extra == "graph"
Requires-Dist: plotly>=5.0.0; extra == "graph"
Requires-Dist: scipy>=1.7.0; extra == "graph"
Requires-Dist: pydot>=1.4.0; extra == "graph"
Requires-Dist: pygraphviz>=1.7; extra == "graph"
Requires-Dist: jinja2>=3.0.0; extra == "graph"
Requires-Dist: werkzeug>=2.0.0; extra == "graph"
Provides-Extra: visualization
Requires-Dist: py3Dmol>=2.0.0; extra == "visualization"
Requires-Dist: rdkit>=2023.9.1; extra == "visualization"
Requires-Dist: plotly>=5.18.0; extra == "visualization"
Requires-Dist: kaleido>=0.2.1; extra == "visualization"
Requires-Dist: scipy>=1.7.0; extra == "visualization"
Requires-Dist: matplotlib>=3.5.0; extra == "visualization"
Requires-Dist: networkx>=3.4.0; extra == "visualization"
Provides-Extra: space
Requires-Dist: huggingface_hub>=0.34.0; extra == "space"
Requires-Dist: pyyaml>=6.0.0; extra == "space"
Requires-Dist: requests>=2.32.0; extra == "space"
Provides-Extra: all
Requires-Dist: tooluniverse[dev,docs,embedding,graph,ml,space,visualization]; extra == "all"
Provides-Extra: build
Requires-Dist: pyinstaller>=6.0.0; extra == "build"
Dynamic: license-file
